hgnc_queries/__init__.py
hgnc_queries/api.py
hgnc_queries/conversion.py
hgnc_queries/queries.py
hgnc_queries-0.1.0.dist-info/LICENCE
hgnc_queries-0.1.0.dist-info/METADATA
hgnc_queries-0.1.0.dist-info/WHEEL
hgnc_queries-0.1.0.dist-info/top_level.txt
hgnc_queries-0.1.0.dist-info/RECORD
