Metadata-Version: 2.1
Name: hgnc-queries
Version: 0.1.0
Summary: Make HGNC queries for gene symbols
Home-page: https://github.com/NHS-NGS/hgnc_queries
Author: Yujin Kim
Author-email: yujin.kim@hotmail.fr
License: UNKNOWN
Platform: UNKNOWN
Classifier: Programming Language :: Python :: 3
Classifier: License :: OSI Approved :: MIT License
Classifier: Operating System :: OS Independent
Requires-Python: >=3.5
